skydb/__init__.py
skydb/classes.py
skydb/connections.py
skydb/tables.py
skydb/update.py
skydb/sheets/__init__.py
skydb/sheets/google_sheets.py
skydb/sheets/style.py
skydb-0.1.3.dist-info/METADATA
skydb-0.1.3.dist-info/WHEEL
skydb-0.1.3.dist-info/top_level.txt
skydb-0.1.3.dist-info/RECORD
